Workbook
Name Slicer_Date_Received__Month: #N/A

Sheet Dashboard
D5: =GETPIVOTDATA("[Measures].[True_Revenue]",Calcs!$A$3) -> 834310.8 | H5: =GETPIVOTDATA("[Measures].[True_Expense]",Calcs!$A$3) -> 772780.36 | L5: =GETPIVOTDATA("[Measures].[Net_Profit]",Calcs!$A$3) -> 61530.44 | P5: =GETPIVOTDATA("[Measures].[Saving Rates]",Calcs!$A$46) -> 0.19369281 | T5: =GETPIVOTDATA("[Measures].[Mapping Accuracy]",Calcs!$A$64,"[CleanedSheet].[Macro_Category]","[CleanedSheet].[Macro_Category].&[Unreconciled]") -> 0.96533595

Sheet Master2
A1: Date Received | B1: Month | C1: Account_ID | D1: Amount | E1: Transaction_Details | F1: Transaction_Type | G1: Category | H1: Type | I1: Month_Sort | J1: Fiscal_Quarter | K1: Total | L1: Flow | M1: Entity | N1: Macro_Category
A2: 45659 | B2: January | C2: 816 | D2: 17015 | E2: Sent to M_Account | F2: Expense | G2: Saving Account | H2: Debit | I2: 1 | J2: 1 | K2: -17015 | L2: Outflow | M2: M_Account | N2: Financial Account
A3: 45660 | B3: January | C3: 384 | D3: 1500 | E3: Received from CD | F3: Income | G3: Transfer | H3: Credit | I3: 1 | J3: 1 | K3: 1500 | L3: Inflow | M3: CD | N3: Payments
A4: 45661 | B4: January | C4: 3957 | D4: 181 | E4: Sent to Kimio old number | F4: Expense | G4: Phone Utilities | H4: Debit | I4: 1 | J4: 1 | K4: -181 | L4: Outflow | M4: Kimio old number | N4: Personal Expense
A5: 45662 | B5: January | C5: 6406 | D5: 1800 | E5: Received from AX | F5: Income | G5: Transfer | H5: Credit | I5: 1 | J5: 1 | K5: 1800 | L5: Inflow | M5: AX | N5: Payments
A6: 45663 | B6: January | C6: 816 | D6: 2015 | E6: Sent to M_Account | F6: Expense | G6: Saving Account | H6: Debit | I6: 1 | J6: 1 | K6: -2015 | L6: Outflow | M6: M_Account | N6: Financial Account
A7: 45664 | B7: January | C7: 559 | D7: 400 | E7: Sent to CA | F7: Expense | G7: Transfer | H7: Debit | I7: 1 | J7: 1 | K7: -400 | L7: Outflow | M7: CA | N7: Payments
A8: 45666 | B8: January | C8: 5097 | D8: 1500 | E8: Received from BI | F8: Income | G8: Transfer | H8: Credit | I8: 1 | J8: 1 | K8: 1500 | L8: Inflow | M8: BI | N8: Payments
A9: 45666 | B9: January | C9: 6807 | D9: 3000 | E9: Received from AV | F9: Income | G9: Transfer | H9: Credit | I9: 1 | J9: 1 | K9: 3000 | L9: Inflow | M9: AV | N9: Payments
A10: 45667 | B10: January | C10: 4969 | D10: 21 | E10: Sent to BuchioSmart | F10: Expense | G10: Phone Utilities | H10: Debit | I10: 1 | J10: 1 | K10: -21 | L10: Outflow | M10: BuchioSmart | N10: Personal Expense
A11: 45667 | B11: January | C11: 1082 | D11: 3500 | E11: Sent to BV | F11: Expense | G11: Transfer | H11: Debit | I11: 1 | J11: 1 | K11: -3500 | L11: Outflow | M11: BV | N11: Payments
A12: 45667 | B12: January | C12: 5572 | D12: 5173 | E12: Received from BG | F12: Income | G12: Transfer | H12: Credit | I12: 1 | J12: 1 | K12: 5173 | L12: Inflow | M12: BG | N12: Payments
A13: 45668 | B13: January | C13: 559 | D13: 400 | E13: Received from CA | F13: Income | G13: Transfer | H13: Credit | I13: 1 | J13: 1 | K13: 400 | L13: Inflow | M13: CA | N13: Payments
... A598: 46022 | B598: December | C598: 6115 | D598: 4000 | E598: Received from DD | F598: Income | G598: Transfer | H598: Credit | I598: 12 | J598: 4 | K598: 4000 | L598: Inflow | M598: DD | N598: Payments

Sheet Calcs
I2: =A23 -> Fixed Expense | J2: =A24 -> Government Payment | K2: =A25 -> Monthly Expense | L2: =A26 -> Personal Expense
A3: Row Labels | B3: Revenue | C3: Expense | D3: Net Profit | F3: Category | G3: Transfer | I3: =GETPIVOTDATA("[Measures].[Sum of Amount]",$A$22,"[CleanedSheet].[Macro_Category]","[CleanedSheet].[Macro_Category].&[Fixed Expense]") -> 185000 | J3: =GETPIVOTDATA("[Measures].[Sum of Amount]",$A$22,"[CleanedSheet].[Macro_Category]","[CleanedSheet].[Macro_Category].&[Government Payment]") -> 85598.91 | K3: =GETPIVOTDATA("[Measures].[Sum of Amount]",$A$22,"[CleanedSheet].[Macro_Category]","[CleanedSheet].[Macro_Category].&[Monthly Expense]") -> 492214.45 | L3: =GETPIVOTDATA("[Measures].[Sum of Amount]",$A$22,"[CleanedSheet].[Macro_Category]","[CleanedSheet].[Macro_Category].&[Personal Expense]") -> 9967
A4: Jan | B4: 56635 | C4: 93742.09 | D4: -37107.09 | F4: Date Received (Month) | G4: All
A5: Feb | B5: 65231 | C5: 47727.67 | D5: 17503.33
A6: Mar | B6: 78601 | C6: 70306.54 | D6: 8294.46 | F6: Row Labels | G6: True_Revenue
A7: Apr | B7: 63142 | C7: 58605.71 | D7: 4536.29 | F7: Jas | G7: 75600
A8: May | B8: 76602 | C8: 75457.96 | D8: 1144.04 | F8: CJMen | G8: 63000
A9: Jun | B9: 112292 | C9: 68281.83 | D9: 44010.17 | F9: AX | G9: 34200
A10: Jul | B10: 71581 | C10: 56672.21 | D10: 14908.79 | F10: AC | G10: 32000
A11: Aug | B11: 58312 | C11: 60561.01 | D11: -2249.01 | F11: DD | G11: 28000
A12: Sep | B12: 54362 | C12: 58051.46 | D12: -3689.46 | F12: BT | G12: 25300
A13: Oct | B13: 74732 | C13: 62669.81 | D13: 12062.19 | F13: AQ | G13: 25000
A14: Nov | B14: 78499.8 | C14: 63376.39 | D14: 15123.41 | F14: NF | G14: 23860
A15: Dec | B15: 44321 | C15: 57327.68 | D15: -13006.68 | F15: BY | G15: 19800
A16: Grand Total | B16: 834310.8 | C16: 772780.36 | D16: 61530.44 | F16: AH | G16: 19000
F17: Grand Total | G17: 345760
A20: Flow | B20: Outflow | D20: Flow | E20: Inflow
D21: Macro_Category | E21: Payments
A22: Row Labels | B22: Sum of Amount
A23: Fixed Expense | B23: 185000 | D23: Row Labels | E23: Sum of Amount
A24: Government Payment | B24: 85598.91 | D24: AJ | E24: 16500
A25: Monthly Expense | B25: 492214.45 | D25: AQ | E25: 25000
A26: Personal Expense | B26: 9967 | D26: AX | E26: 34200
A27: Grand Total | B27: 772780.36 | D27: BP | E27: 12000
D28: BY | E28: 19800
D29: CJMen | E29: 63000
A30: Row Labels | B30: Sum of Amount | D30: DD | E30: 28000
A31: Unreconciled | D31: Jas | E31: 75600
A32: Jan | B32: 700 | D32: K.UB | E32: 141000
A33: Feb | B33: 3305 | D33: NF | E33: 23860
A34: Mar | B34: 14702 | D34: Grand Total | E34: 438960
A35: Apr | B35: 8210.19
A36: May | B36: 8910
A37: Jun | B37: 10715
A38: Jul | B38: 43370
A39: Aug | B39: 6000
A40: Oct | B40: 910
A41: Nov | B41: 3760
A42: Grand Total | B42: 100582.19
A46: Row Labels | B46: Sum of Amount | C46: True_Revenue | D46: Saving Rates
A47: Monthly Savings
A48: Jan | B48: 7000 | C48: 56635 | D48: 0.12359848
A49: Feb | B49: 13000 | C49: 65231 | D49: 0.19929175
A50: Mar | B50: 15000 | C50: 78601 | D50: 0.19083727
A51: Apr | B51: 15000 | C51: 63142 | D51: 0.23755979
A52: May | B52: 13000 | C52: 76602 | D52: 0.16970836
A53: Jun | B53: 12000 | C53: 112292 | D53: 0.10686425
A54: Jul | B54: 16000 | C54: 71581 | D54: 0.223523
A55: Aug | B55: 15000 | C55: 58312 | D55: 0.25723693
A56: Sep | B56: 14600 | C56: 54362 | D56: 0.26856996
A57: Oct | B57: 10000 | C57: 74732 | D57: 0.13381149
A58: Nov | B58: 16000 | C58: 78499.8 | D58: 0.20382218
A59: Dec | B59: 15000 | C59: 44321 | D59: 0.33844002
A60: Grand Total | B60: 161600 | C60: 834310.8 | D60: 0.19369281
A64: Row Labels | B64: Sum of Amount | C64: Mapping Accuracy
A65: Financial Account | B65: 565020 | C65: 0.96533595
A66: Fixed Expense | B66: 185000 | C66: 0.96533595
A67: Ginvestment | B67: 3556.19 | C67: 0.96533595
A68: Government Payment | B68: 85598.91 | C68: 0.96533595
A69: Miscellaneous | B69: 19044 | C69: 0.96533595
A70: Monthly Expense | B70: 492214.45 | C70: 0.96533595
A71: Monthly Savings | B71: 161600 | C71: 0.96533595
A72: Payments | B72: 1179391.8 | C72: 0.96533595
A73: Personal Expense | B73: 9967 | C73: 0.96533595
A74: Repayment | B74: 99653.51 | C74: 0.96533595
A75: Unreconciled | B75: 100582.19 | C75: 0.96533595
A76: Grand Total | B76: 2901628 | C76: 0.96533595

Sheet Mapping
A1: Account ID | B1: Description | C1: MasterKey | D1: Entity (Who/What) | E1: Category | F1: Macro-Category
A2: N/a | B2: Sss | C2: Sss | D2: Sss Government | E2: Government | F2: Government Payment
A3: 9950 | B3: N/a | C3: 9950 | D3: Carmenio | E3: Transfer | F3: Payments
A4: 9807 | B4: N/a | C4: 9807 | D4: Unidentified | E4: Undisclosed | F4: Unreconciled
A5: 9619 | B5: N/a | C5: 9619 | D5: Unidentified | E5: Undisclosed | F5: Unreconciled
A6: 9438 | B6: N/a | C6: 9438 | D6: Unidentified | E6: Undisclosed | F6: Unreconciled
A7: 9162 | B7: N/a | C7: 9162 | D7: AA | E7: Transfer | F7: Payments
A8: 9090 | B8: N/a | C8: 9090 | D8: AB | E8: Transfer | F8: Payments
A9: 9032 | B9: N/a | C9: 9032 | D9: AC | E9: Transfer | F9: Payments
A10: 8758 | B10: N/a | C10: 8758 | D10: AD | E10: Transfer | F10: Payments
A11: 8652 | B11: N/a | C11: 8652 | D11: BuchioSmart | E11: Phone Utilities | F11: Personal Expense
A12: 8562 | B12: N/a | C12: 8562 | D12: Unidentified | E12: Undisclosed | F12: Unreconciled
A13: 8497 | B13: N/a | C13: 8497 | D13: AE | E13: Transfer | F13: Payments
A14: 8306 | B14: N/a | C14: 8306 | D14: Unidentified | E14: Undisclosed | F14: Unreconciled
... A47: 6119 | B47: N/a | C47: 6119 | D47: BA | E47: Transfer | F47: Payments
A48: 6115 | B48: BpiDD | C48: BpiDD | D48: DD | E48: Transfer | F48: Payments
A49: 6009 | B49: N/a | C49: 6009 | D49: BC | E49: Transfer | F49: Payments
A50: 5988 | B50: N/a | C50: 5988 | D50: Unidentified | E50: Undisclosed | F50: Unreconciled
A51: 5854 | B51: N/a | C51: 5854 | D51: JM | E51: Transfer | F51: Payments
A52: 5791 | B52: N/a | C52: 5791 | D52: Ethel | E52: Transfer | F52: Payments
A53: 5780 | B53: N/a | C53: 5780 | D53: Unidentified | E53: Undisclosed | F53: Unreconciled
A54: 5763 | B54: JasBpi | C54: 5763 | D54: Jas | E54: Transfer | F54: Payments
A55: 5715 | B55: N/a | C55: 5715 | D55: Unidentified | E55: Undisclosed | F55: Unreconciled
A56: 5680 | B56: N/a | C56: 5680 | D56: BE | E56: Transfer | F56: Payments
A57: 5672 | B57: N/a | C57: 5672 | D57: BF | E57: Transfer | F57: Payments
A58: 5572 | B58: N/a | C58: 5572 | D58: BG | E58: Transfer | F58: Payments
A59: 5340 | B59: N/a | C59: 5340 | D59: BH | E59: Transfer | F59: Payments
A60: 5125 | B60: N/a | C60: 5125 | D60: Unidentified | E60: Undisclosed | F60: Unreconciled
... A111: 0 | B111: N/a | C111: 0 | D111: CH | E111: Transfer | F111: Payments
A112: 1 | B112: Home | C112: Home | D112: Rent Home | E112: Home Expense | F112: Fixed Expense
A113: 2 | B113: Insurance | C113: Insurance | D113: Fwd | E113: Insurance Fwd | F113: Monthly Expense
A114: 3 | B114: Efund | C114: Efund | D114: Emergency | E114: Savings | F114: Monthly Savings
A115: 4 | B115: Education | C115: Education | D115: School | E115: Savings | F115: Monthly Savings
A116: 5 | B116: Plant | C116: Plant | D116: Crop | E116: Plantation | F116: Monthly Expense
A117: 6 | B117: Gloan | C117: Gloan | D117: GLoan | E117: Debt | F117: Repayment
A118: 7 | B118: Ginvest | C118: Ginvest | D118: Invest | E118: Investment | F118: Ginvestment
A119: 8 | B119: Credit card | C119: Credit card | D119: Credit Card payment | E119: Card payment | F119: Monthly Expense
A120: 9 | B120: Pagibig | C120: Pagibig | D120: Pagibig Fund | E120: Government | F120: Government Payment
A121: 10 | B121: Petty | C121: Petty | D121: Personal Cash | E121: Personal | F121: Monthly Expense
A122: 11 | B122: Loklok | C122: Loklok | D122: Tv Subscription | E122: Subscription | F122: Monthly Expense
A123: 12 | B123: Easytrip | C123: Easytrip | D123: Nlex | E123: Toll Fee | F123: Miscellaneous
... A132: 21 | B132: PJLInc | C132: PJLInc | D132: PJLInc | E132: PJLInc | F132: Payments
A133: 2470 | B133: N/a | C133: 2470 | D133: Unidentified | E133: Undisclosed | F133: Unreconciled

Sheet  Master
A1: Date Received | B1: Month | C1: Id | D1: Category | E1: Type | F1: Amount
A2: 45659 | B2: January | C2: 816 | D2: =_xlfn.XLOOKUP(C2, Mapping!$C:$C, Mapping!$E:$E, "Check ID") -> Saving Account | E2: Debit | F2: 17015
A3: 45661 | B3: January | C3: 3957 | D3: =_xlfn.XLOOKUP(C3, Mapping!$C:$C, Mapping!$E:$E, "Check ID") -> Phone Utilities | E3: Debit | F3: 181
A4: 45663 | B4: January | C4: 816 | D4: =_xlfn.XLOOKUP(C4, Mapping!$C:$C, Mapping!$E:$E, "Check ID") -> Saving Account | E4: Debit | F4: 2015
A5: 45664 | B5: January | C5: 559 | D5: =_xlfn.XLOOKUP(C5, Mapping!$C:$C, Mapping!$E:$E, "Check ID") -> Transfer | E5: Debit | F5: 400
A6: 45667 | B6: January | C6: 4969 | D6: =_xlfn.XLOOKUP(C6, Mapping!$C:$C, Mapping!$E:$E, "Check ID") -> Phone Utilities | E6: Debit | F6: 21
A7: 45667 | B7: January | C7: 1082 | D7: =_xlfn.XLOOKUP(C7, Mapping!$C:$C, Mapping!$E:$E, "Check ID") -> Transfer | E7: Debit | F7: 3500
A8: 45669 | B8: January | C8: 5988 | D8: =_xlfn.XLOOKUP(C8, Mapping!$C:$C, Mapping!$E:$E, "Check ID") -> Undisclosed | E8: Debit | F8: 700
A9: 45672 | B9: January | C9: Pagibig | D9: =_xlfn.XLOOKUP(C9, Mapping!$C:$C, Mapping!$E:$E, "Check ID") -> Government | E9: Debit | F9: 12131.81
A10: 45673 | B10: January | C10: 1862 | D10: =_xlfn.XLOOKUP(C10, Mapping!$C:$C, Mapping!$E:$E, "Check ID") -> Transfer | E10: Debit | F10: 7000
A11: 45673 | B11: January | C11: 9032 | D11: =_xlfn.XLOOKUP(C11, Mapping!$C:$C, Mapping!$E:$E, "Check ID") -> Transfer | E11: Debit | F11: 10000
A12: 45674 | B12: January | C12: 816 | D12: =_xlfn.XLOOKUP(C12, Mapping!$C:$C, Mapping!$E:$E, "Check ID") -> Saving Account | E12: Debit | F12: 24015
A13: 45676 | B13: January | C13: 3957 | D13: =_xlfn.XLOOKUP(C13, Mapping!$C:$C, Mapping!$E:$E, "Check ID") -> Phone Utilities | E13: Debit | F13: 181
A14: 45677 | B14: January | C14: Gloan | D14: =_xlfn.XLOOKUP(C14, Mapping!$C:$C, Mapping!$E:$E, "Check ID") -> Debt | E14: Debit | F14: 2730.83
A15: 45677 | B15: January | C15: 1773 | D15: =_xlfn.XLOOKUP(C15, Mapping!$C:$C, Mapping!$E:$E, "Check ID") -> Transfer | E15: Debit | F15: 3000
A16: 45682 | B16: January | C16: 7910 | D16: =_xlfn.XLOOKUP(C16, Mapping!$C:$C, Mapping!$E:$E, "Check ID") -> Transfer | E16: Debit | F16: 1000
A17: 45687 | B17: January | C17: 9032 | D17: =_xlfn.XLOOKUP(C17, Mapping!$C:$C, Mapping!$E:$E, "Check ID") -> Transfer | E17: Debit | F17: 10000
A18: 45688 | B18: January | C18: 7261 | D18: =_xlfn.XLOOKUP(C18, Mapping!$C:$C, Mapping!$E:$E, "Check ID") -> Transfer | E18: Debit | F18: 5000
A19: 45688 | B19: January | C19: 7479 | D19: =_xlfn.XLOOKUP(C19, Mapping!$C:$C, Mapping!$E:$E, "Check ID") -> Transfer | E19: Debit | F19: 2000
A20: 45660 | B20: January | C20: 384 | D20: =_xlfn.XLOOKUP(C20, Mapping!$C:$C, Mapping!$E:$E, "Check ID") -> Transfer | E20: Credit | F20: 1500
A21: 45662 | B21: January | C21: 6406 | D21: =_xlfn.XLOOKUP(C21, Mapping!$C:$C, Mapping!$E:$E, "Check ID") -> Transfer | E21: Credit | F21: 1800
A22: 45666 | B22: January | C22: 6807 | D22: =_xlfn.XLOOKUP(C22, Mapping!$C:$C, Mapping!$E:$E, "Check ID") -> Transfer | E22: Credit | F22: 3000
A23: 45666 | B23: January | C23: 5097 | D23: =_xlfn.XLOOKUP(C23, Mapping!$C:$C, Mapping!$E:$E, "Check ID") -> Transfer | E23: Credit | F23: 1500
A24: 45667 | B24: January | C24: 5572 | D24: =_xlfn.XLOOKUP(C24, Mapping!$C:$C, Mapping!$E:$E, "Check ID") -> Transfer | E24: Credit | F24: 5173
A25: 45668 | B25: January | C25: 559 | D25: =_xlfn.XLOOKUP(C25, Mapping!$C:$C, Mapping!$E:$E, "Check ID") -> Transfer | E25: Credit | F25: 400
A26: 45670 | B26: January | C26: 5763 | D26: =_xlfn.XLOOKUP(C26, Mapping!$C:$C, Mapping!$E:$E, "Check ID") -> Transfer | E26: Credit | F26: 3600
... A36: 45675 | B36: January | C36: 7261 | D36: =_xlfn.XLOOKUP(C36, Mapping!$C:$C, Mapping!$E:$E, "Check ID") -> Transfer | E36: Credit | F36: 1200
A37: 45675 | B37: January | C37: Ginvest | D37: =_xlfn.XLOOKUP(C37, Mapping!$C:$C, Mapping!$E:$E, "Check ID") -> Investment | E37: Credit | F37: 27.01
A38: 45676 | B38: January | C38: 308 | D38: =_xlfn.XLOOKUP(C38, Mapping!$C:$C, Mapping!$E:$E, "Check ID") -> Transfer | E38: Credit | F38: 1000
A39: 45676 | B39: January | C39: 5854 | D39: =_xlfn.XLOOKUP(C39, Mapping!$C:$C, Mapping!$E:$E, "Check ID") -> Transfer | E39: Credit | F39: 1500
A40: 45676 | B40: January | C40: 8072 | D40: =_xlfn.XLOOKUP(C40, Mapping!$C:$C, Mapping!$E:$E, "Check ID") -> Transfer | E40: Credit | F40: 1500
A41: 45682 | B41: January | C41: 7133 | D41: =_xlfn.XLOOKUP(C41, Mapping!$C:$C, Mapping!$E:$E, "Check ID") -> Transfer | E41: Credit | F41: 1500
A42: 45687 | B42: January | C42: 1862 | D42: =_xlfn.XLOOKUP(C42, Mapping!$C:$C, Mapping!$E:$E, "Check ID") -> Transfer | E42: Credit | F42: 1400
A43: 45687 | B43: January | C43: 7910 | D43: =_xlfn.XLOOKUP(C43, Mapping!$C:$C, Mapping!$E:$E, "Check ID") -> Transfer | E43: Credit | F43: 1200
A44: 45687 | B44: January | C44: 9032 | D44: =_xlfn.XLOOKUP(C44, Mapping!$C:$C, Mapping!$E:$E, "Check ID") -> Transfer | E44: Credit | F44: 2000
A45: 45687 | B45: January | C45: BpiDD | D45: =_xlfn.XLOOKUP(C45, Mapping!$C:$C, Mapping!$E:$E, "Check ID") -> Transfer | E45: Credit | F45: 3000
A46: 45687 | B46: January | C46: 7276 | D46: =_xlfn.XLOOKUP(C46, Mapping!$C:$C, Mapping!$E:$E, "Check ID") -> Transfer | E46: Credit | F46: 3000
A47: 45687 | B47: January | C47: 1082 | D47: =_xlfn.XLOOKUP(C47, Mapping!$C:$C, Mapping!$E:$E, "Check ID") -> Transfer | E47: Credit | F47: 700
A48: 45687 | B48: January | C48: 9162 | D48: =_xlfn.XLOOKUP(C48, Mapping!$C:$C, Mapping!$E:$E, "Check ID") -> Transfer | E48: Credit | F48: 2000
A49: 45689 | B49: February | C49: 816 | D49: =_xlfn.XLOOKUP(C49, Mapping!$C:$C, Mapping!$E:$E, "Check ID") -> Saving Account | E49: Debit | F49: 32515
A50: 45690 | B50: February | C50: 1862 | D50: =_xlfn.XLOOKUP(C50, Mapping!$C:$C, Mapping!$E:$E, "Check ID") -> Transfer | E50: Debit | F50: 10000
A51: 45690 | B51: February | C51: 816 | D51: =_xlfn.XLOOKUP(C51, Mapping!$C:$C, Mapping!$E:$E, "Check ID") -> Saving Account | E51: Debit | F51: 5515
A52: 45691 | B52: February | C52: 3957 | D52: =_xlfn.XLOOKUP(C52, Mapping!$C:$C, Mapping!$E:$E, "Check ID") -> Phone Utilities | E52: Debit | F52: 151
A53: 45696 | B53: February | C53: 7910 | D53: =_xlfn.XLOOKUP(C53, Mapping!$C:$C, Mapping!$E:$E, "Check ID") -> Transfer | E53: Debit | F53: 1000
A54: 45700 | B54: February | C54: 1082 | D54: =_xlfn.XLOOKUP(C54, Mapping!$C:$C, Mapping!$E:$E, "Check ID") -> Transfer | E54: Debit | F54: 2500
A55: 45702 | B55: February | C55: 1082 | D55: =_xlfn.XLOOKUP(C55, Mapping!$C:$C, Mapping!$E:$E, "Check ID") -> Transfer | E55: Debit | F55: 3500
A56: 45702 | B56: February | C56: 7336 | D56: =_xlfn.XLOOKUP(C56, Mapping!$C:$C, Mapping!$E:$E, "Check ID") -> Transfer | E56: Debit | F56: 5000
A57: 45703 | B57: February | C57: 9032 | D57: =_xlfn.XLOOKUP(C57, Mapping!$C:$C, Mapping!$E:$E, "Check ID") -> Transfer | E57: Debit | F57: 10000
... A61: 45705 | B61: February | C61: 3957 | D61: =_xlfn.XLOOKUP(C61, Mapping!$C:$C, Mapping!$E:$E, "Check ID") -> Phone Utilities | E61: Debit | F61: 181
A62: 45708 | B62: February | C62: Gloan | D62: =_xlfn.XLOOKUP(C62, Mapping!$C:$C, Mapping!$E:$E, "Check ID") -> Debt | E62: Debit | F62: 2730.83
A63: 45708 | B63: February | C63: 2037 | D63: =_xlfn.XLOOKUP(C63, Mapping!$C:$C, Mapping!$E:$E, "Check ID") -> Undisclosed | E63: Debit | F63: 1000
A64: 45711 | B64: February | C64: 5715 | D64: =_xlfn.XLOOKUP(C64, Mapping!$C:$C, Mapping!$E:$E, "Check ID") -> Undisclosed | E64: Debit | F64: 290
A65: 45714 | B65: February | C65: 2488 | D65: =_xlfn.XLOOKUP(C65, Mapping!$C:$C, Mapping!$E:$E, "Check ID") -> Undisclosed | E65: Debit | F65: 2015
A66: 45690 | B66: February | C66: 1773 | D66: =_xlfn.XLOOKUP(C66, Mapping!$C:$C, Mapping!$E:$E, "Check ID") -> Transfer | E66: Credit | F66: 4000
A67: 45690 | B67: February | C67: 6807 | D67: =_xlfn.XLOOKUP(C67, Mapping!$C:$C, Mapping!$E:$E, "Check ID") -> Transfer | E67: Credit | F67: 3000
A68: 45690 | B68: February | C68: 8497 | D68: =_xlfn.XLOOKUP(C68, Mapping!$C:$C, Mapping!$E:$E, "Check ID") -> Transfer | E68: Credit | F68: 5500
A69: 45699 | B69: February | C69: 5791 | D69: =_xlfn.XLOOKUP(C69, Mapping!$C:$C, Mapping!$E:$E, "Check ID") -> Transfer | E69: Credit | F69: 2000
A70: 45699 | B70: February | C70: 308 | D70: =_xlfn.XLOOKUP(C70, Mapping!$C:$C, Mapping!$E:$E, "Check ID") -> Transfer | E70: Credit | F70: 1000
A71: 45702 | B71: February | C71: 295 | D71: =_xlfn.XLOOKUP(C71, Mapping!$C:$C, Mapping!$E:$E, "Check ID") -> Transfer | E71: Credit | F71: 1600
A72: 45702 | B72: February | C72: 7276 | D72: =_xlfn.XLOOKUP(C72, Mapping!$C:$C, Mapping!$E:$E, "Check ID") -> Transfer | E72: Credit | F72: 3000
A73: 45703 | B73: February | C73: 7910 | D73: =_xlfn.XLOOKUP(C73, Mapping!$C:$C, Mapping!$E:$E, "Check ID") -> Transfer | E73: Credit | F73: 2400
A74: 45703 | B74: February | C74: 9032 | D74: =_xlfn.XLOOKUP(C74, Mapping!$C:$C, Mapping!$E:$E, "Check ID") -> Transfer | E74: Credit | F74: 2000
... A89: 45718 | B89: March | C89: 8306 | D89: =_xlfn.XLOOKUP(C89, Mapping!$C:$C, Mapping!$E:$E, "Check ID") -> Undisclosed | E89: Debit | F89: 6000
A90: 45721 | B90: March | C90: Pagibig | D90: =_xlfn.XLOOKUP(C90, Mapping!$C:$C, Mapping!$E:$E, "Check ID") -> Government | E90: Debit | F90: 6505
A91: 45726 | B91: March | C91: 1059 | D91: =_xlfn.XLOOKUP(C91, Mapping!$C:$C, Mapping!$E:$E, "Check ID") -> Phone Utilities | E91: Debit | F91: 151
A92: 45728 | B92: March | C92: 2470 | D92: =_xlfn.XLOOKUP(C92, Mapping!$C:$C, Mapping!$E:$E, "Check ID") -> Undisclosed | E92: Debit | F92: 3500
A93: 45730 | B93: March | C93: Pagibig | D93: =_xlfn.XLOOKUP(C93, Mapping!$C:$C, Mapping!$E:$E, "Check ID") -> Government | E93: Debit | F93: 6505
A94: 45730 | B94: March | C94: 9032 | D94: =_xlfn.XLOOKUP(C94, Mapping!$C:$C, Mapping!$E:$E, "Check ID") -> Transfer | E94: Debit | F94: 10000
A95: 45732 | B95: March | C95: 816 | D95: =_xlfn.XLOOKUP(C95, Mapping!$C:$C, Mapping!$E:$E, "Check ID") -> Saving Account | E95: Debit | F95: 29015
A96: 45734 | B96: March | C96: 8562 | D96: =_xlfn.XLOOKUP(C96, Mapping!$C:$C, Mapping!$E:$E, "Check ID") -> Undisclosed | E96: Debit | F96: 202
A97: 45737 | B97: March | C97: Gloan | D97: =_xlfn.XLOOKUP(C97, Mapping!$C:$C, Mapping!$E:$E, "Check ID") -> Debt | E97: Debit | F97: 2730.81
A98: 45718 | B98: March | C98: 4969 | D98: =_xlfn.XLOOKUP(C98, Mapping!$C:$C, Mapping!$E:$E, "Check ID") -> Phone Utilities | E98: Debit | F98: 31
A99: 45744 | B99: March | C99: 908 | D99: =_xlfn.XLOOKUP(C99, Mapping!$C:$C, Mapping!$E:$E, "Check ID") -> Undisclosed | E99: Debit | F99: 5000
A100: 45744 | B100: March | C100: 9032 | D100: =_xlfn.XLOOKUP(C100, Mapping!$C:$C, Mapping!$E:$E, "Check ID") -> Transfer | E100: Debit | F100: 10000
A101: 45744 | B101: March | C101: 1059 | D101: =_xlfn.XLOOKUP(C101, Mapping!$C:$C, Mapping!$E:$E, "Check ID") -> Phone Utilities | E101: Debit | F101: 151
A102: 45744 | B102: March | C102: 7261 | D102: =_xlfn.XLOOKUP(C102, Mapping!$C:$C, Mapping!$E:$E, "Check ID") -> Transfer | E102: Debit | F102: 5000
A103: 45747 | B103: March | C103: 816 | D103: =_xlfn.XLOOKUP(C103, Mapping!$C:$C, Mapping!$E:$E, "Check ID") -> Saving Account | E103: Debit | F103: 15015
A104: 45747 | B104: March | C104: Ginvest | D104: =_xlfn.XLOOKUP(C104, Mapping!$C:$C, Mapping!$E:$E, "Check ID") -> Investment | E104: Debit | F104: 500
A105: 45717 | B105: March | C105: 4360 | D105: =_xlfn.XLOOKUP(C105, Mapping!$C:$C, Mapping!$E:$E, "Check ID") -> Transfer | E105: Credit | F105: 1500
A106: 45717 | B106: March | C106: 7910 | D106: =_xlfn.XLOOKUP(C106, Mapping!$C:$C, Mapping!$E:$E, "Check ID") -> Transfer | E106: Credit | F106: 3000
A107: 45718 | B107: March | C107: 4494 | D107: =_xlfn.XLOOKUP(C107, Mapping!$C:$C, Mapping!$E:$E, "Check ID") -> Transfer | E107: Credit | F107: 1500
A108: 45718 | B108: March | C108: 7336 | D108: =_xlfn.XLOOKUP(C108, Mapping!$C:$C, Mapping!$E:$E, "Check ID") -> Transfer | E108: Credit | F108: 800
A109: 45721 | B109: March | C109: 7507 | D109: =_xlfn.XLOOKUP(C109, Mapping!$C:$C, Mapping!$E:$E, "Check ID") -> Transfer | E109: Credit | F109: 431
A110: 45722 | B110: March | C110: 5854 | D110: =_xlfn.XLOOKUP(C110, Mapping!$C:$C, Mapping!$E:$E, "Check ID") -> Transfer | E110: Credit | F110: 2000
A111: 45723 | B111: March | C111: 4360 | D111: =_xlfn.XLOOKUP(C111, Mapping!$C:$C, Mapping!$E:$E, "Check ID") -> Transfer | E111: Credit | F111: 1500
A112: 45728 | B112: March | C112: 5791 | D112: =_xlfn.XLOOKUP(C112, Mapping!$C:$C, Mapping!$E:$E, "Check ID") -> Transfer | E112: Credit | F112: 1500
A113: 45729 | B113: March | C113: 6406 | D113: =_xlfn.XLOOKUP(C113, Mapping!$C:$C, Mapping!$E:$E, "Check ID") -> Transfer | E113: Credit | F113: 1800
A114: 45729 | B114: March | C114: 7261 | D114: =_xlfn.XLOOKUP(C114, Mapping!$C:$C, Mapping!$E:$E, "Check ID") -> Transfer | E114: Credit | F114: 1600
A115: 45730 | B115: March | C115: 4530 | D115: =_xlfn.XLOOKUP(C115, Mapping!$C:$C, Mapping!$E:$E, "Check ID") -> Saving Account | E115: Credit | F115: 6000
A116: 45730 | B116: March | C116: 295 | D116: =_xlfn.XLOOKUP(C116, Mapping!$C:$C, Mapping!$E:$E, "Check ID") -> Transfer | E116: Credit | F116: 1600
... A136: 45745 | B136: March | C136: 5763 | D136: =_xlfn.XLOOKUP(C136, Mapping!$C:$C, Mapping!$E:$E, "Check ID") -> Transfer | E136: Credit | F136: 3600
A137: 45746 | B137: March | C137: BpiDD | D137: =_xlfn.XLOOKUP(C137, Mapping!$C:$C, Mapping!$E:$E, "Check ID") -> Transfer | E137: Credit | F137: 2000
A138: 45746 | B138: March | C138: 384 | D138: =_xlfn.XLOOKUP(C138, Mapping!$C:$C, Mapping!$E:$E, "Check ID") -> Transfer | E138: Credit | F138: 1200
A139: 45748 | B139: April | C139: 2488 | D139: =_xlfn.XLOOKUP(C139, Mapping!$C:$C, Mapping!$E:$E, "Check ID") -> Undisclosed | E139: Debit | F139: 3515
A140: 45748 | B140: April | C140: Psa | D140: =_xlfn.XLOOKUP(C140, Mapping!$C:$C, Mapping!$E:$E, "Check ID") -> Certificate | E140: Debit | F140: 330
A141: 45748 | B141: April | C141: 7910 | D141: =_xlfn.XLOOKUP(C141, Mapping!$C:$C, Mapping!$E:$E, "Check ID") -> Transfer | E141: Debit | F141: 1000
A142: 45748 | B142: April | C142: 1082 | D142: =_xlfn.XLOOKUP(C142, Mapping!$C:$C, Mapping!$E:$E, "Check ID") -> Transfer | E142: Debit | F142: 5000
A143: 45748 | B143: April | C143: 4639 | D143: =_xlfn.XLOOKUP(C143, Mapping!$C:$C, Mapping!$E:$E, "Check ID") -> Undisclosed | E143: Debit | F143: 400
A144: 45748 | B144: April | C144: 21 | D144: =_xlfn.XLOOKUP(C144, Mapping!$C:$C, Mapping!$E:$E, "Check ID") -> Undisclosed | E144: Debit | F144: 1695.19
A145: 45748 | B145: April | C145: 4639 | D145: =_xlfn.XLOOKUP(C145, Mapping!$C:$C, Mapping!$E:$E, "Check ID") -> Undisclosed | E145: Debit | F145: 2100
...
